coininfo_collector/__init__.py
coininfo_collector/coinClient.py
coininfo_collector/coinCommons.py
coininfo_collector/coinScheduler.py
coininfo_collector/coinSummary.py
coininfo_collector/coinSummaryCache.py
coininfo_collector/db_manager.py
coininfo_collector/ijMarketPriceGlobal.py
coininfo_collector/marketPairs.py
coininfo_collector/priceInExchange.py
coininfo_collector/priceInExchangeCache.py
coininfo_collector/s3Interface.py
coininfo_collector/sparklineWriter.py
coininfo_collector/ssfixedJobs.py
coininfo_collector/web_requests_async.py
coininfo_collector-0.0.54.dist-info/LICENSE
coininfo_collector-0.0.54.dist-info/METADATA
coininfo_collector-0.0.54.dist-info/WHEEL
coininfo_collector-0.0.54.dist-info/top_level.txt
coininfo_collector-0.0.54.dist-info/RECORD
