Metadata-Version: 2.1
Name: coininfo-collector
Version: 0.0.54
Summary: unlimit tail coinfo_collector
Home-page: https://...
Author: chase
Author-email: 
License: UNKNOWN
Download-URL: https://...
Keywords: utail,coinfo_collector
Platform: UNKNOWN
Classifier: Programming Language :: Python :: 3
Classifier: Programming Language :: Python :: 3.2
Classifier: Programming Language :: Python :: 3.3
Classifier: Programming Language :: Python :: 3.4
Classifier: Programming Language :: Python :: 3.5
Classifier: Programming Language :: Python :: 3.6
Classifier: Programming Language :: Python :: 3.7
Requires-Python: >=3
